CHANGELOG.rst
CONTRIBUTING.rst
LICENSE-MIT.txt
MANIFEST.in
README.rst
TODO.rst
setup.py
signature.txt
bin/fjoin
bin/fsplit
fsplit/__init__.py
fsplit/debugger_fjoin.py
fsplit/debugger_fsplit.py
fsplit/exce.py
fsplit/info.py
fsplit/main.py
fsplit/oswrapper.py
fsplit/tar.py
fsplit3.egg-info/PKG-INFO
fsplit3.egg-info/SOURCES.txt
fsplit3.egg-info/dependency_links.txt
fsplit3.egg-info/top_level.txt
fsplit/parse/__init__.py
fsplit/parse/opfjoin.py
fsplit/parse/opfsplit.py
fsplit/parse/parent_parser.py
fsplit/tests/__init__.py
fsplit/tests/test_cdir.py
fsplit/tests/test_createTar.py
fsplit/tests/test_extractTar.py
fsplit/tests/test_rdir.py
fsplit/tests/test_split_join.py