Metadata-Version: 2.1
Name: fsplit3
Version: 0.0.0
Summary: Split files into small portable chunks
Home-page: https://github.com/shantanuk98/fsplit2
Author: shantanu kumar
Author-email: shantanu020198@gmail.com
License: MIT
Keywords: files chunk split parts portable join tar
Classifier: Development Status :: 3 - Alpha
Classifier: License :: OSI Approved :: MIT License
Classifier: Environment :: Console
Classifier: Natural Language :: English
License-File: LICENSE-MIT.txt
